pymomenta/__init__.py
pymomenta-0.0.1.dist-info/METADATA
pymomenta-0.0.1.dist-info/WHEEL
pymomenta-0.0.1.dist-info/RECORD
