Metadata-Version: 2.4
Name: pymomenta
Version: 0.0.1
Summary: Python wrapper for the high-performance Julia package Momenta.jl
Author-email: Dazhong Wu <wudz800@gmail.com>
Classifier: License :: OSI Approved :: MIT License
Classifier: Operating System :: OS Independent
Classifier: Programming Language :: Python :: 3
Requires-Python: >=3.7
